RLuligoClinicalParsing/LuligoParsingNotes.py
RLuligoClinicalParsing/LuligoRemoveEmptyNotes.py
RLuligoClinicalParsing/__init__.py
RLuligoClinicalParsing/add.py
RLuligoClinicalParsing/extras/__init__.py
RLuligoClinicalParsing/extras/divide.py
RLuligoClinicalParsing/extras/multiply.py
RLuligoClinicalParsing-0.1.2.dist-info/LICENSE
RLuligoClinicalParsing-0.1.2.dist-info/METADATA
RLuligoClinicalParsing-0.1.2.dist-info/WHEEL
RLuligoClinicalParsing-0.1.2.dist-info/top_level.txt
RLuligoClinicalParsing-0.1.2.dist-info/RECORD
